{
  "id": "media-examples-item",
  "title": "Media",
  "content": [
    {
      "type": "title",
      "titleData": {
        "text": "Image Block Example",
        "level": "2",
        "enableAnchorLink": true
      }
    },
    {
      "type": "image",
      "imageData": {
        "type": "single",
        "image": {
          "src": "/SST-Docs/data/v1.1/images/Image_Example_1.png",
          "alt": "Image Example 1"
        },
        "scale": "0.5",
        "alignment": "center"
      }
    },
    {
      "type": "title",
      "titleData": {
        "text": "Image Compare Examples",
        "level": "2",
        "enableAnchorLink": true
      }
    },
    {
      "type": "image",
      "imageData": {
        "type": "compare",
        "beforeImage": {
          "src": "/SST-Docs/data/v1.1/images/Image_Example_1.png",
          "alt": "Image Example 1"
        },
        "afterImage": {
          "src": "/SST-Docs/data/v1.1/images/Image_Example_2.png",
          "alt": "Image Example 2"
        },
        "alignment": "center"
      }
    },
    {
      "type": "image",
      "imageData": {
        "type": "slider",
        "beforeImage": {
          "src": "/SST-Docs/data/v1.1/images/Image_Example_1.png",
          "alt": "Image Example 1"
        },
        "afterImage": {
          "src": "/SST-Docs/data/v1.1/images/Image_Example_2.png",
          "alt": "Image Example 2"
        },
        "scale": 0.5,
        "alignment": "center",
        "showPercentage": true
      }
    },
    {
      "type": "title",
      "titleData": {
        "text": "Image Carousel Example",
        "level": "2",
        "enableAnchorLink": true
      }
    },
    {
      "type": "image",
      "imageData": {
        "type": "carousel",
        "images": [
          {
            "src": "/SST-Docs/data/v1.1/images/Image_Example_1.png",
            "alt": "Image Example 1",
            "caption": "First example image"
          },
          {
            "src": "/SST-Docs/data/v1.1/images/Image_Example_2.png",
            "alt": "Image Example 2",
            "caption": "Second example image"
          }
        ],
        "scale": 0.5,
        "alignment": "center",
        "carouselOptions": {
          "loop": true,
          "gap": "1rem",
          "arrows": true,
          "pagination": false,
          "autoplay": false
        }
      }
    },
    {
      "type": "title",
      "titleData": {
        "text": "Image Grid Example",
        "level": "2",
        "enableAnchorLink": true
      }
    },
    {
      "type": "image",
      "imageData": {
        "type": "grid",
        "images": [
          {
            "src": "/SST-Docs/data/v1.1/images/Image_Example_1.png",
            "alt": "Image Example 1",
            "caption": "First example image"
          },
          {
            "src": "/SST-Docs/data/v1.1/images/Image_Example_2.png",
            "alt": "Image Example 2",
            "caption": "Second example image"
          },
          {
            "src": "/SST-Docs/data/v1.1/images/Image_Example_1.png",
            "alt": "Image Example 1",
            "caption": "First example image"
          },
          {
            "src": "/SST-Docs/data/v1.1/images/Image_Example_2.png",
            "alt": "Image Example 2",
            "caption": "Second example image"
          }
        ],
        "alignment": "center"
      }
    },
    {
      "type": "title",
      "titleData": {
        "text": "Audio Example",
        "level": "2",
        "enableAnchorLink": true
      }
    },
    {
      "type": "audio",
      "audioData": {
        "src": "/SST-Docs/data/v1.1/audio/AudioSample.mp3",
        "mimeType": "audio/mpeg",
        "caption": "Ambient sample"
      }
    },
    {
      "type": "title",
      "titleData": {
        "text": "Youtube Video Example",
        "level": "2",
        "enableAnchorLink": true
      }
    },
    {
      "type": "youtube",
      "youtubeVideoId": "1bSEHTbrisQ",
      "scale": "0.8"
    }
  ]
}